{
  "created_at_utc": "2026-07-12T20:38:22.427523+00:00",
  "checkpoint": "D:\\INSTANT TRAINING\\2nd Sprint\\2nd project\\models\\exports\\production_road_damage_model.pt",
  "onnx": "D:\\INSTANT TRAINING\\2nd Sprint\\2nd project\\models\\exports\\production_road_damage_model.onnx",
  "images_checked": 20,
  "confidence_threshold": 0.25,
  "image_size": 640,
  "min_box_iou_tolerance": 0.95,
  "max_conf_delta_tolerance": 0.05,
  "pytorch_detections": 62,
  "onnx_detections": 64,
  "matched_detections": 58,
  "failed_images": 12,
  "min_matched_iou": 0.0,
  "mean_matched_iou": 0.9041575825431739,
  "max_conf_delta": 0.16870832443237305,
  "max_box_abs_delta_px": 1331.6967468261719,
  "passed": false,
  "details": "D:\\INSTANT TRAINING\\2nd Sprint\\2nd project\\reports\\final_comparison\\onnx_equivalence_details.csv"
}